spoken2written/__init__.py
spoken2written/spoken2written.py
spoken2written-0.1.4.dist-info/METADATA
spoken2written-0.1.4.dist-info/WHEEL
spoken2written-0.1.4.dist-info/top_level.txt
spoken2written-0.1.4.dist-info/RECORD
