Metadata-Version: 2.1
Name: spoken2written
Version: 0.1.4
Summary: This package is to translate spoken languag to its written form
Home-page: https://github.com/HerambVD/spoken2written
Author: Heramb Devbhankar
Author-email: heramb1711@gmail.com
License: MIT
Platform: UNKNOWN
Classifier: Development Status :: 4 - Beta
Classifier: License :: OSI Approved :: MIT License
Classifier: Programming Language :: Python
Classifier: Programming Language :: Python :: 3.5
Classifier: Programming Language :: Python :: 3.6
Classifier: Programming Language :: Python :: 3.7
Classifier: Topic :: Software Development :: Libraries
Classifier: Topic :: Software Development :: Libraries :: Python Modules
Classifier: Intended Audience :: Developers
Requires-Python: >=3.5
Requires-Dist: spacy
Requires-Dist: word2number
